pypardiso/__init__.py
pypardiso/pardiso_wrapper.py
pypardiso/scipy_aliases.py
pypardiso_mopt-0.1.0.dist-info/LICENSE.txt
pypardiso_mopt-0.1.0.dist-info/METADATA
pypardiso_mopt-0.1.0.dist-info/WHEEL
pypardiso_mopt-0.1.0.dist-info/RECORD
