Metadata-Version: 2.1
Name: pypardiso-mopt
Version: 0.1.0
Summary: Python interface to the Intel MKL Pardiso library to solve large sparse linear systems of equations
License: LICENSE.txt
Author: Adrian Haas
Requires-Python: >=3.8
Classifier: License :: Other/Proprietary License
Classifier: Programming Language :: Python :: 3
Classifier: Programming Language :: Python :: 3.8
Classifier: Programming Language :: Python :: 3.9
Classifier: Programming Language :: Python :: 3.10
Classifier: Programming Language :: Python :: 3.11
Requires-Dist: mkl (!=2024.0)
Requires-Dist: numpy (>=1.26)
Requires-Dist: scipy (>=1.11)
